Workbook

Sheet Assumptions
A1: ABC MoneyLoan — Amazon Reseller Projection
A2: FBA vs FBM · 3 employees · 66.6% gross margin · FBA uses existing store staff
A4: ITEM ECONOMICS
A5: Average selling price | B5: 30 | C5: Editable. Typical resale price per item.
A6: Average product cost (COGS) | B6: 10 | C6: What the item costs ABC (pawn basis).
A7: Gross margin % | B7: =1-B6/B5 -> 0.66666667 | C7: Equals 1 − cost/price. Target 66.6%.
A9: AMAZON FEES
A10: Referral commission % | B10: 0.15 | C10: Per item. 8% electronics … 15% most goods.
A11: FBA fulfillment fee / item | B11: 4.5 | C11: Flat pick/pack/ship (2026 ~$3–5). FBA only.
A12: FBA storage / item (avg) | B12: 0.5 | C12: Monthly storage until it sells. FBA only.
A13: Amazon Professional plan / month | B13: 40 | C13: Flat monthly overhead (both methods).
A15: FBM (SELF-FULFILL)
A16: FBM outbound shipping / item | B16: 6 | C16: Postage + box ABC pays to ship to buyer.
A18: LABOR (key difference between the two)
A19: Number of employees | B19: 3 | C19: Existing store staff.
A20: Wage per employee / month | B20: 2600 | C20: Assumption ≈ $15/hr full-time. Set to actual.
A21: Store payroll (reference) | B21: =B19*B20 -> 7800 | C21: Employees × wage. Already paid for the shop.
A22: FBA labor charged to Amazon (% payroll) | B22: 0 | C22: 0% = existing staff list in spare time; no new payroll.
A23: FBM labor charged to Amazon (% payroll) | B23: 1 | C23: Packing & shipping is real added work — a dedicated crew.
A24: FBA monthly labor | B24: =B21*B22 -> 0 | C24: Payroll × FBA share.
A25: FBM monthly labor | B25: =B21*B23 -> 7800 | C25: Payroll × FBM share.
A27: VOLUME
A28: Units / month — snapshot | B28: 900 | C28: Volume used on the 'Monthly' sheet.
A29: Month-1 units (projection) | B29: 700 | C29: Starting volume for the 12-month projection.
A30: Monthly growth rate | B30: 0.06 | C30: Unit growth applied each month.
A32: LABOR CAPACITY (units / employee / month)
A33: FBM capacity / employee | B33: 350 | C33: Fewer — staff pack & ship every order.
A34: FBA capacity / employee | B34: 700 | C34: More — Amazon fulfills; staff source & list only.
A35: FBM total capacity | B35: =B19*B33 -> 1050 | C35: Employees × FBM capacity.
A36: FBA total capacity | B36: =B19*B34 -> 2100 | C36: Employees × FBA capacity.
A38: Blue = editable input (yellow). Black = formula. KEY: FBA labor defaults to 0% — with FBA, Amazon fulfills, so existing store staff run it in spare time and ABC adds no payroll. FBM defaults to 100% because packing & shipping ties up a dedicated crew. If existing staff also cover FBM in spare time, lower B23 — but then the FBM capacity limit (B35) bites sooner. Fee/storage are 2026 estimates; confirm in Seller Central.

Sheet Per-Unit
A1: Per-Unit Economics
A2: One average item, before monthly overhead (plan + any labor)
A3: Per item | B3: FBA | C3: FBM
A4: Selling price | B4: =Assumptions!$B$5 -> 30 | C4: =Assumptions!$B$5 -> 30
A5: Product cost (COGS) | B5: =-Assumptions!$B$6 -> -10 | C5: =-Assumptions!$B$6 -> -10
A6: Gross profit | B6: =B4+B5 -> 20 | C6: =C4+C5 -> 20
A7: Gross margin % | B7: =B6/B4 -> 0.66666667 | C7: =C6/C4 -> 0.66666667
A8: Referral fee | B8: =-B4*Assumptions!$B$10 -> -4.5 | C8: =-C4*Assumptions!$B$10 -> -4.5
A9: FBA fulfillment fee | B9: =-Assumptions!$B$11 -> -4.5 | C9: 0
A10: FBA storage | B10: =-Assumptions!$B$12 -> -0.5 | C10: 0
A11: FBM shipping | B11: 0 | C11: =-Assumptions!$B$16 -> -6
A12: Contribution / unit | B12: =B6+B8+B9+B10+B11 -> 10.5 | C12: =C6+C8+C9+C10+C11 -> 9.5
A13: Contribution margin % | B13: =B12/B4 -> 0.35 | C13: =C12/C4 -> 0.31666667
A16: Contribution/unit = what one sale adds before the $40 plan and any labor. Labor differs by method and lives on the Monthly/Projection sheets, not here.

Sheet Monthly
A1: Monthly P&L — FBA vs FBM
A2: Snapshot volume (Assumptions!B28), capped at capacity. FBA adds no payroll; FBM carries a dedicated crew.
A3: Line | B3: FBA | C3: FBM
A4: Units sold / month | B4: =MIN(Assumptions!$B$28,Assumptions!$B$36) -> 900 | C4: =MIN(Assumptions!$B$28,Assumptions!$B$35) -> 900
A5: Revenue | B5: =B4*Assumptions!$B$5 -> 27000 | C5: =C4*Assumptions!$B$5 -> 27000
A6: Product cost (COGS) | B6: =-B4*Assumptions!$B$6 -> -9000 | C6: =-C4*Assumptions!$B$6 -> -9000
A7: Gross profit | B7: =B5+B6 -> 18000 | C7: =C5+C6 -> 18000
A8: Referral fees | B8: =-B4*Assumptions!$B$5*Assumptions!$B$10 -> -4050 | C8: =-C4*Assumptions!$B$5*Assumptions!$B$10 -> -4050
A9: FBA fulfillment fees | B9: =-B4*Assumptions!$B$11 -> -4050 | C9: 0
A10: FBA storage | B10: =-B4*Assumptions!$B$12 -> -450 | C10: 0
A11: FBM shipping | B11: 0 | C11: =-C4*Assumptions!$B$16 -> -5400
A12: Amazon plan (monthly) | B12: =-Assumptions!$B$13 -> -40 | C12: =-Assumptions!$B$13 -> -40
A13: Labor charged to Amazon | B13: =-Assumptions!$B$24 -> 0 | C13: =-Assumptions!$B$25 -> -7800
A14: Net operating profit | B14: =B7+B8+B9+B10+B11+B12+B13 -> 9410 | C14: =C7+C8+C9+C10+C11+C12+C13 -> 710
A15: Net margin % | B15: =B14/B5 -> 0.34851852 | C15: =C14/C5 -> 0.026296296
A17: Supporting metrics
A18: Contribution / unit | B18: ='Per-Unit'!B12 -> 10.5 | C18: ='Per-Unit'!C12 -> 9.5
A19: Fixed costs / month (plan + labor) | B19: =Assumptions!$B$13+Assumptions!$B$24 -> 40 | C19: =Assumptions!$B$13+Assumptions!$B$25 -> 7840
A20: Break-even units / month | B20: =B19/B18 -> 3.8095238 | C20: =C19/C18 -> 825.26316
A21: Labor capacity (units) | B21: =Assumptions!$B$36 -> 2100 | C21: =Assumptions!$B$35 -> 1050
A22: Capacity utilization % | B22: =B4/B21 -> 0.42857143 | C22: =C4/C21 -> 0.85714286
A24: Verdict | B24: =IF(B14>C14,"FBA nets more here","FBM nets more here") -> FBA nets more here
A25: Difference (FBA − FBM) / month | B25: =B14-C14 -> 8700
A27: Big driver: FBA labor = $0 by default (existing store staff, no new payroll), while FBM carries a dedicated crew (Assumptions B23). That's why FBA looks far stronger. FBM still hits a labor-capacity ceiling as volume grows. Change the blue inputs — especially B22/B23 — to match ABC's real staffing.

Sheet Projection
A1: 12-Month Projection — FBA vs FBM
A2: Demand grows from Month-1 units; each method capped at its labor capacity. FBA carries no new payroll.
A4: Month | B4: Demand | C4: FBA units | D4: FBA net | E4: FBA cum. | F4: FBM units | G4: FBM net | H4: FBM cum.
A5: 1 | B5: =Assumptions!$B$29 -> 700 | C5: =MIN(B5,Assumptions!$B$36) -> 700 | D5: =C5*'Per-Unit'!$B$12-Assumptions!$B$13-Assumptions!$B$24 -> 7310 | E5: =D5 -> 7310 | F5: =MIN(B5,Assumptions!$B$35) -> 700 | G5: =F5*'Per-Unit'!$C$12-Assumptions!$B$13-Assumptions!$B$25 -> -1190 | H5: =G5 -> -1190
A6: 2 | B6: =ROUND(B5*(1+Assumptions!$B$30),0) -> 742 | C6: =MIN(B6,Assumptions!$B$36) -> 742 | D6: =C6*'Per-Unit'!$B$12-Assumptions!$B$13-Assumptions!$B$24 -> 7751 | E6: =E5+D6 -> 15061 | F6: =MIN(B6,Assumptions!$B$35) -> 742 | G6: =F6*'Per-Unit'!$C$12-Assumptions!$B$13-Assumptions!$B$25 -> -791 | H6: =H5+G6 -> -1981
A7: 3 | B7: =ROUND(B6*(1+Assumptions!$B$30),0) -> 787 | C7: =MIN(B7,Assumptions!$B$36) -> 787 | D7: =C7*'Per-Unit'!$B$12-Assumptions!$B$13-Assumptions!$B$24 -> 8223.5 | E7: =E6+D7 -> 23284.5 | F7: =MIN(B7,Assumptions!$B$35) -> 787 | G7: =F7*'Per-Unit'!$C$12-Assumptions!$B$13-Assumptions!$B$25 -> -363.5 | H7: =H6+G7 -> -2344.5
A8: 4 | B8: =ROUND(B7*(1+Assumptions!$B$30),0) -> 834 | C8: =MIN(B8,Assumptions!$B$36) -> 834 | D8: =C8*'Per-Unit'!$B$12-Assumptions!$B$13-Assumptions!$B$24 -> 8717 | E8: =E7+D8 -> 32001.5 | F8: =MIN(B8,Assumptions!$B$35) -> 834 | G8: =F8*'Per-Unit'!$C$12-Assumptions!$B$13-Assumptions!$B$25 -> 83 | H8: =H7+G8 -> -2261.5
A9: 5 | B9: =ROUND(B8*(1+Assumptions!$B$30),0) -> 884 | C9: =MIN(B9,Assumptions!$B$36) -> 884 | D9: =C9*'Per-Unit'!$B$12-Assumptions!$B$13-Assumptions!$B$24 -> 9242 | E9: =E8+D9 -> 41243.5 | F9: =MIN(B9,Assumptions!$B$35) -> 884 | G9: =F9*'Per-Unit'!$C$12-Assumptions!$B$13-Assumptions!$B$25 -> 558 | H9: =H8+G9 -> -1703.5
A10: 6 | B10: =ROUND(B9*(1+Assumptions!$B$30),0) -> 937 | C10: =MIN(B10,Assumptions!$B$36) -> 937 | D10: =C10*'Per-Unit'!$B$12-Assumptions!$B$13-Assumptions!$B$24 -> 9798.5 | E10: =E9+D10 -> 51042 | F10: =MIN(B10,Assumptions!$B$35) -> 937 | G10: =F10*'Per-Unit'!$C$12-Assumptions!$B$13-Assumptions!$B$25 -> 1061.5 | H10: =H9+G10 -> -642
A11: 7 | B11: =ROUND(B10*(1+Assumptions!$B$30),0) -> 993 | C11: =MIN(B11,Assumptions!$B$36) -> 993 | D11: =C11*'Per-Unit'!$B$12-Assumptions!$B$13-Assumptions!$B$24 -> 10386.5 | E11: =E10+D11 -> 61428.5 | F11: =MIN(B11,Assumptions!$B$35) -> 993 | G11: =F11*'Per-Unit'!$C$12-Assumptions!$B$13-Assumptions!$B$25 -> 1593.5 | H11: =H10+G11 -> 951.5
A12: 8 | B12: =ROUND(B11*(1+Assumptions!$B$30),0) -> 1053 | C12: =MIN(B12,Assumptions!$B$36) -> 1053 | D12: =C12*'Per-Unit'!$B$12-Assumptions!$B$13-Assumptions!$B$24 -> 11016.5 | E12: =E11+D12 -> 72445 | F12: =MIN(B12,Assumptions!$B$35) -> 1050 | G12: =F12*'Per-Unit'!$C$12-Assumptions!$B$13-Assumptions!$B$25 -> 2135 | H12: =H11+G12 -> 3086.5
A13: 9 | B13: =ROUND(B12*(1+Assumptions!$B$30),0) -> 1116 | C13: =MIN(B13,Assumptions!$B$36) -> 1116 | D13: =C13*'Per-Unit'!$B$12-Assumptions!$B$13-Assumptions!$B$24 -> 11678 | E13: =E12+D13 -> 84123 | F13: =MIN(B13,Assumptions!$B$35) -> 1050 | G13: =F13*'Per-Unit'!$C$12-Assumptions!$B$13-Assumptions!$B$25 -> 2135 | H13: =H12+G13 -> 5221.5
A14: 10 | B14: =ROUND(B13*(1+Assumptions!$B$30),0) -> 1183 | C14: =MIN(B14,Assumptions!$B$36) -> 1183 | D14: =C14*'Per-Unit'!$B$12-Assumptions!$B$13-Assumptions!$B$24 -> 12381.5 | E14: =E13+D14 -> 96504.5 | F14: =MIN(B14,Assumptions!$B$35) -> 1050 | G14: =F14*'Per-Unit'!$C$12-Assumptions!$B$13-Assumptions!$B$25 -> 2135 | H14: =H13+G14 -> 7356.5
A15: 11 | B15: =ROUND(B14*(1+Assumptions!$B$30),0) -> 1254 | C15: =MIN(B15,Assumptions!$B$36) -> 1254 | D15: =C15*'Per-Unit'!$B$12-Assumptions!$B$13-Assumptions!$B$24 -> 13127 | E15: =E14+D15 -> 109631.5 | F15: =MIN(B15,Assumptions!$B$35) -> 1050 | G15: =F15*'Per-Unit'!$C$12-Assumptions!$B$13-Assumptions!$B$25 -> 2135 | H15: =H14+G15 -> 9491.5
A16: 12 | B16: =ROUND(B15*(1+Assumptions!$B$30),0) -> 1329 | C16: =MIN(B16,Assumptions!$B$36) -> 1329 | D16: =C16*'Per-Unit'!$B$12-Assumptions!$B$13-Assumptions!$B$24 -> 13914.5 | E16: =E15+D16 -> 123546 | F16: =MIN(B16,Assumptions!$B$35) -> 1050 | G16: =F16*'Per-Unit'!$C$12-Assumptions!$B$13-Assumptions!$B$25 -> 2135 | H16: =H15+G16 -> 11626.5
A17: Total | B17: =SUM(B5:B16) -> 11812 | C17: =SUM(C5:C16) -> 11812 | D17: =SUM(D5:D16) -> 123546 | F17: =SUM(F5:F16) -> 11127 | G17: =SUM(G5:G16) -> 11626.5
A19: Year-1 net — FBA | C19: =D17 -> 123546
A20: Year-1 net — FBM | C20: =G17 -> 11626.5
A21: Advantage (FBA − FBM) | C21: =D17-G17 -> 111919.5

Sheet Break-Even
A1: Break-Even — Net Profit by Monthly Volume
A2: Net profit at each volume (capped at capacity). Where a line crosses $0 is that method's break-even.
A4: Units / month | B4: FBA net | C4: FBM net
A5: 0 | B5: =MIN(A5,Assumptions!$B$36)*'Per-Unit'!$B$12-Assumptions!$B$13-Assumptions!$B$24 -> -40 | C5: =MIN(A5,Assumptions!$B$35)*'Per-Unit'!$C$12-Assumptions!$B$13-Assumptions!$B$25 -> -7840
A6: 100 | B6: =MIN(A6,Assumptions!$B$36)*'Per-Unit'!$B$12-Assumptions!$B$13-Assumptions!$B$24 -> 1010 | C6: =MIN(A6,Assumptions!$B$35)*'Per-Unit'!$C$12-Assumptions!$B$13-Assumptions!$B$25 -> -6890
A7: 200 | B7: =MIN(A7,Assumptions!$B$36)*'Per-Unit'!$B$12-Assumptions!$B$13-Assumptions!$B$24 -> 2060 | C7: =MIN(A7,Assumptions!$B$35)*'Per-Unit'!$C$12-Assumptions!$B$13-Assumptions!$B$25 -> -5940
A8: 300 | B8: =MIN(A8,Assumptions!$B$36)*'Per-Unit'!$B$12-Assumptions!$B$13-Assumptions!$B$24 -> 3110 | C8: =MIN(A8,Assumptions!$B$35)*'Per-Unit'!$C$12-Assumptions!$B$13-Assumptions!$B$25 -> -4990
A9: 400 | B9: =MIN(A9,Assumptions!$B$36)*'Per-Unit'!$B$12-Assumptions!$B$13-Assumptions!$B$24 -> 4160 | C9: =MIN(A9,Assumptions!$B$35)*'Per-Unit'!$C$12-Assumptions!$B$13-Assumptions!$B$25 -> -4040
A10: 500 | B10: =MIN(A10,Assumptions!$B$36)*'Per-Unit'!$B$12-Assumptions!$B$13-Assumptions!$B$24 -> 5210 | C10: =MIN(A10,Assumptions!$B$35)*'Per-Unit'!$C$12-Assumptions!$B$13-Assumptions!$B$25 -> -3090
A11: 600 | B11: =MIN(A11,Assumptions!$B$36)*'Per-Unit'!$B$12-Assumptions!$B$13-Assumptions!$B$24 -> 6260 | C11: =MIN(A11,Assumptions!$B$35)*'Per-Unit'!$C$12-Assumptions!$B$13-Assumptions!$B$25 -> -2140
A12: 700 | B12: =MIN(A12,Assumptions!$B$36)*'Per-Unit'!$B$12-Assumptions!$B$13-Assumptions!$B$24 -> 7310 | C12: =MIN(A12,Assumptions!$B$35)*'Per-Unit'!$C$12-Assumptions!$B$13-Assumptions!$B$25 -> -1190
A13: 800 | B13: =MIN(A13,Assumptions!$B$36)*'Per-Unit'!$B$12-Assumptions!$B$13-Assumptions!$B$24 -> 8360 | C13: =MIN(A13,Assumptions!$B$35)*'Per-Unit'!$C$12-Assumptions!$B$13-Assumptions!$B$25 -> -240
A14: 900 | B14: =MIN(A14,Assumptions!$B$36)*'Per-Unit'!$B$12-Assumptions!$B$13-Assumptions!$B$24 -> 9410 | C14: =MIN(A14,Assumptions!$B$35)*'Per-Unit'!$C$12-Assumptions!$B$13-Assumptions!$B$25 -> 710
A15: 1000 | B15: =MIN(A15,Assumptions!$B$36)*'Per-Unit'!$B$12-Assumptions!$B$13-Assumptions!$B$24 -> 10460 | C15: =MIN(A15,Assumptions!$B$35)*'Per-Unit'!$C$12-Assumptions!$B$13-Assumptions!$B$25 -> 1660
A16: 1100 | B16: =MIN(A16,Assumptions!$B$36)*'Per-Unit'!$B$12-Assumptions!$B$13-Assumptions!$B$24 -> 11510 | C16: =MIN(A16,Assumptions!$B$35)*'Per-Unit'!$C$12-Assumptions!$B$13-Assumptions!$B$25 -> 2135
... A20: 1500 | B20: =MIN(A20,Assumptions!$B$36)*'Per-Unit'!$B$12-Assumptions!$B$13-Assumptions!$B$24 -> 15710 | C20: =MIN(A20,Assumptions!$B$35)*'Per-Unit'!$C$12-Assumptions!$B$13-Assumptions!$B$25 -> 2135
A22: Break-even units | B22: =(Assumptions!$B$13+Assumptions!$B$24)/'Per-Unit'!$B$12 -> 3.8095238 | C22: =(Assumptions!$B$13+Assumptions!$B$25)/'Per-Unit'!$C$12 -> 825.26316
A23: Break-even = fixed costs (plan + labor) ÷ contribution per unit

Sheet Scenarios
A1: Scenario Comparison — Referral × Fulfillment
A2: Contribution, break-even and monthly net at snapshot volume. Referral is editable (blue). Labor per method from Assumptions.
A4: Scenario | B4: Referral | C4: Method | D4: Contribution/unit | E4: Break-even units | F4: Net @ snapshot | G4: Net margin %
A5: Low fee · FBM | B5: 0.08 | C5: FBM | D5: =Assumptions!$B$5-Assumptions!$B$6-Assumptions!$B$5*B5-Assumptions!$B$16 -> 11.6 | E5: =(Assumptions!$B$13+Assumptions!$B$25)/D5 -> 675.86207 | F5: =MIN(Assumptions!$B$28,Assumptions!$B$35)*D5-Assumptions!$B$13-Assumptions!$B$25 -> 2600 | G5: =F5/(MIN(Assumptions!$B$28,Assumptions!$B$35)*Assumptions!$B$5) -> 0.096296296
A6: Low fee · FBA | B6: 0.08 | C6: FBA | D6: =Assumptions!$B$5-Assumptions!$B$6-Assumptions!$B$5*B6-Assumptions!$B$11-Assumptions!$B$12 -> 12.6 | E6: =(Assumptions!$B$13+Assumptions!$B$24)/D6 -> 3.1746032 | F6: =MIN(Assumptions!$B$28,Assumptions!$B$36)*D6-Assumptions!$B$13-Assumptions!$B$24 -> 11300 | G6: =F6/(MIN(Assumptions!$B$28,Assumptions!$B$36)*Assumptions!$B$5) -> 0.41851852
A7: Typical · FBM | B7: 0.15 | C7: FBM | D7: =Assumptions!$B$5-Assumptions!$B$6-Assumptions!$B$5*B7-Assumptions!$B$16 -> 9.5 | E7: =(Assumptions!$B$13+Assumptions!$B$25)/D7 -> 825.26316 | F7: =MIN(Assumptions!$B$28,Assumptions!$B$35)*D7-Assumptions!$B$13-Assumptions!$B$25 -> 710 | G7: =F7/(MIN(Assumptions!$B$28,Assumptions!$B$35)*Assumptions!$B$5) -> 0.026296296
A8: Typical · FBA | B8: 0.15 | C8: FBA | D8: =Assumptions!$B$5-Assumptions!$B$6-Assumptions!$B$5*B8-Assumptions!$B$11-Assumptions!$B$12 -> 10.5 | E8: =(Assumptions!$B$13+Assumptions!$B$24)/D8 -> 3.8095238 | F8: =MIN(Assumptions!$B$28,Assumptions!$B$36)*D8-Assumptions!$B$13-Assumptions!$B$24 -> 9410 | G8: =F8/(MIN(Assumptions!$B$28,Assumptions!$B$36)*Assumptions!$B$5) -> 0.34851852
A10: Net @ snapshot uses Assumptions!B28 units, capped at each method's capacity.
